<annotation>
	<folder></folder>
	<filename>img_04_1306_jpg.rf.299bf44b23f4c588f987fd4ae2156414.jpg</filename>
	<path>img_04_1306_jpg.rf.299bf44b23f4c588f987fd4ae2156414.jpg</path>
	<source>
		<database>roboflow.ai</database>
	</source>
	<size>
		<width>640</width>
		<height>640</height>
		<depth>3</depth>
	</size>
	<segmented>0</segmented>
	<object>
		<name>tugboat</name>
		<pose>Unspecified</pose>
		<truncated>0</truncated>
		<difficult>0</difficult>
		<occluded>0</occluded>
		<bndbox>
			<xmin>476</xmin>
			<xmax>641</xmax>
			<ymin>387</ymin>
			<ymax>619</ymax>
		</bndbox>
	</object>
</annotation>
