<annotation>
	<folder></folder>
	<filename>img_01_0781_jpg.rf.edd20c82f6d8fd55ce38508e0f3629dd.jpg</filename>
	<path>img_01_0781_jpg.rf.edd20c82f6d8fd55ce38508e0f3629dd.jpg</path>
	<source>
		<database>roboflow.ai</database>
	</source>
	<size>
		<width>640</width>
		<height>640</height>
		<depth>3</depth>
	</size>
	<segmented>0</segmented>
	<object>
		<name>Portanaves</name>
		<pose>Unspecified</pose>
		<truncated>0</truncated>
		<difficult>0</difficult>
		<occluded>0</occluded>
		<bndbox>
			<xmin>56</xmin>
			<xmax>641</xmax>
			<ymin>43</ymin>
			<ymax>539</ymax>
		</bndbox>
	</object>
</annotation>
