<annotation>
	<folder></folder>
	<filename>img_04_0596_jpg.rf.6382e8a78fae11c19b7637eda5bb7587.jpg</filename>
	<path>img_04_0596_jpg.rf.6382e8a78fae11c19b7637eda5bb7587.jpg</path>
	<source>
		<database>roboflow.ai</database>
	</source>
	<size>
		<width>640</width>
		<height>640</height>
		<depth>3</depth>
	</size>
	<segmented>0</segmented>
	<object>
		<name>tugboat</name>
		<pose>Unspecified</pose>
		<truncated>0</truncated>
		<difficult>0</difficult>
		<occluded>0</occluded>
		<bndbox>
			<xmin>318</xmin>
			<xmax>502</xmax>
			<ymin>276</ymin>
			<ymax>426</ymax>
		</bndbox>
	</object>
</annotation>
