<annotation>
	<folder></folder>
	<filename>00001404_jpg.rf.2ecdb99891f76a5a2ecf7fd0aa631010.jpg</filename>
	<path>00001404_jpg.rf.2ecdb99891f76a5a2ecf7fd0aa631010.jpg</path>
	<source>
		<database>roboflow.ai</database>
	</source>
	<size>
		<width>512</width>
		<height>512</height>
		<depth>3</depth>
	</size>
	<segmented>0</segmented>
	<object>
		<name>helicopter</name>
		<pose>Unspecified</pose>
		<truncated>0</truncated>
		<difficult>0</difficult>
		<occluded>0</occluded>
		<bndbox>
			<xmin>9</xmin>
			<xmax>500</xmax>
			<ymin>2</ymin>
			<ymax>505</ymax>
		</bndbox>
	</object>
</annotation>
