<annotation>
	<folder></folder>
	<filename>00001264_jpg.rf.c637955860e694cae9f90af62cea96b0.jpg</filename>
	<path>00001264_jpg.rf.c637955860e694cae9f90af62cea96b0.jpg</path>
	<source>
		<database>roboflow.ai</database>
	</source>
	<size>
		<width>512</width>
		<height>512</height>
		<depth>3</depth>
	</size>
	<segmented>0</segmented>
	<object>
		<name>helicopter</name>
		<pose>Unspecified</pose>
		<truncated>0</truncated>
		<difficult>0</difficult>
		<occluded>0</occluded>
		<bndbox>
			<xmin>14</xmin>
			<xmax>513</xmax>
			<ymin>19</ymin>
			<ymax>408</ymax>
		</bndbox>
	</object>
</annotation>
