<annotation>
	<folder></folder>
	<filename>img_01_1194_jpg.rf.b6674197ba67c934d5ac1fd80c18bf6f.jpg</filename>
	<path>img_01_1194_jpg.rf.b6674197ba67c934d5ac1fd80c18bf6f.jpg</path>
	<source>
		<database>roboflow.ai</database>
	</source>
	<size>
		<width>512</width>
		<height>512</height>
		<depth>3</depth>
	</size>
	<segmented>0</segmented>
	<object>
		<name>Portanaves</name>
		<pose>Unspecified</pose>
		<truncated>0</truncated>
		<difficult>0</difficult>
		<occluded>0</occluded>
		<bndbox>
			<xmin>167</xmin>
			<xmax>372</xmax>
			<ymin>165</ymin>
			<ymax>341</ymax>
		</bndbox>
	</object>
</annotation>
