<annotation>
	<folder></folder>
	<filename>img_00_0305_jpg.rf.185309c14815bef580a455181579d87c.jpg</filename>
	<path>img_00_0305_jpg.rf.185309c14815bef580a455181579d87c.jpg</path>
	<source>
		<database>roboflow.ai</database>
	</source>
	<size>
		<width>512</width>
		<height>512</height>
		<depth>3</depth>
	</size>
	<segmented>0</segmented>
	<object>
		<name>submarine</name>
		<pose>Unspecified</pose>
		<truncated>0</truncated>
		<difficult>0</difficult>
		<occluded>0</occluded>
		<bndbox>
			<xmin>55</xmin>
			<xmax>452</xmax>
			<ymin>155</ymin>
			<ymax>385</ymax>
		</bndbox>
	</object>
	<object>
		<name>submarine</name>
		<pose>Unspecified</pose>
		<truncated>0</truncated>
		<difficult>0</difficult>
		<occluded>0</occluded>
		<bndbox>
			<xmin>2</xmin>
			<xmax>189</xmax>
			<ymin>100</ymin>
			<ymax>296</ymax>
		</bndbox>
	</object>
</annotation>
