<annotation>
	<folder></folder>
	<filename>img_00_1164_jpg.rf.1d94a851d941a478c15f74333061c6ae.jpg</filename>
	<path>img_00_1164_jpg.rf.1d94a851d941a478c15f74333061c6ae.jpg</path>
	<source>
		<database>roboflow.ai</database>
	</source>
	<size>
		<width>512</width>
		<height>512</height>
		<depth>3</depth>
	</size>
	<segmented>0</segmented>
	<object>
		<name>submarine</name>
		<pose>Unspecified</pose>
		<truncated>0</truncated>
		<difficult>0</difficult>
		<occluded>0</occluded>
		<bndbox>
			<xmin>161</xmin>
			<xmax>384</xmax>
			<ymin>100</ymin>
			<ymax>325</ymax>
		</bndbox>
	</object>
</annotation>
