<annotation>
	<folder></folder>
	<filename>img_02_0062_jpg.rf.a595d9a26746bdaafe0e20cc4c124a0b.jpg</filename>
	<path>img_02_0062_jpg.rf.a595d9a26746bdaafe0e20cc4c124a0b.jpg</path>
	<source>
		<database>roboflow.ai</database>
	</source>
	<size>
		<width>512</width>
		<height>512</height>
		<depth>3</depth>
	</size>
	<segmented>0</segmented>
	<object>
		<name>Fragata</name>
		<pose>Unspecified</pose>
		<truncated>0</truncated>
		<difficult>0</difficult>
		<occluded>0</occluded>
		<bndbox>
			<xmin>25</xmin>
			<xmax>472</xmax>
			<ymin>53</ymin>
			<ymax>478</ymax>
		</bndbox>
	</object>
</annotation>
