<annotation>
	<folder></folder>
	<filename>img_00_0002_jpg.rf.de406aa8a73898dd004cc17ab34193dc.jpg</filename>
	<path>img_00_0002_jpg.rf.de406aa8a73898dd004cc17ab34193dc.jpg</path>
	<source>
		<database>roboflow.ai</database>
	</source>
	<size>
		<width>512</width>
		<height>512</height>
		<depth>3</depth>
	</size>
	<segmented>0</segmented>
	<object>
		<name>submarine</name>
		<pose>Unspecified</pose>
		<truncated>0</truncated>
		<difficult>0</difficult>
		<occluded>0</occluded>
		<bndbox>
			<xmin>72</xmin>
			<xmax>473</xmax>
			<ymin>46</ymin>
			<ymax>393</ymax>
		</bndbox>
	</object>
</annotation>
