<annotation>
	<folder></folder>
	<filename>img_03_0858_jpg.rf.6ceeb4b11963b5af4f8bde96a4faac6e.jpg</filename>
	<path>img_03_0858_jpg.rf.6ceeb4b11963b5af4f8bde96a4faac6e.jpg</path>
	<source>
		<database>roboflow.ai</database>
	</source>
	<size>
		<width>512</width>
		<height>512</height>
		<depth>3</depth>
	</size>
	<segmented>0</segmented>
	<object>
		<name>cruises</name>
		<pose>Unspecified</pose>
		<truncated>0</truncated>
		<difficult>0</difficult>
		<occluded>0</occluded>
		<bndbox>
			<xmin>39</xmin>
			<xmax>471</xmax>
			<ymin>195</ymin>
			<ymax>381</ymax>
		</bndbox>
	</object>
</annotation>
