<annotation>
	<folder></folder>
	<filename>img_04_0426_jpg.rf.690bea6ac131cbc25d9656a586ee7ab9.jpg</filename>
	<path>img_04_0426_jpg.rf.690bea6ac131cbc25d9656a586ee7ab9.jpg</path>
	<source>
		<database>roboflow.ai</database>
	</source>
	<size>
		<width>512</width>
		<height>512</height>
		<depth>3</depth>
	</size>
	<segmented>0</segmented>
	<object>
		<name>tugboat</name>
		<pose>Unspecified</pose>
		<truncated>0</truncated>
		<difficult>0</difficult>
		<occluded>0</occluded>
		<bndbox>
			<xmin>44</xmin>
			<xmax>483</xmax>
			<ymin>93</ymin>
			<ymax>467</ymax>
		</bndbox>
	</object>
</annotation>
