<annotation>
	<folder></folder>
	<filename>00001174_jpg.rf.aafa0940da122d84a37ad192cea529ee.jpg</filename>
	<path>00001174_jpg.rf.aafa0940da122d84a37ad192cea529ee.jpg</path>
	<source>
		<database>roboflow.ai</database>
	</source>
	<size>
		<width>640</width>
		<height>640</height>
		<depth>3</depth>
	</size>
	<segmented>0</segmented>
	<object>
		<name>helicopter</name>
		<pose>Unspecified</pose>
		<truncated>0</truncated>
		<difficult>0</difficult>
		<occluded>0</occluded>
		<bndbox>
			<xmin>1</xmin>
			<xmax>408</xmax>
			<ymin>1</ymin>
			<ymax>480</ymax>
		</bndbox>
	</object>
</annotation>
