<annotation>
	<folder></folder>
	<filename>00001423_jpg.rf.b6b45b6b6f042c08da0fabf00cfdf454.jpg</filename>
	<path>00001423_jpg.rf.b6b45b6b6f042c08da0fabf00cfdf454.jpg</path>
	<source>
		<database>roboflow.ai</database>
	</source>
	<size>
		<width>640</width>
		<height>640</height>
		<depth>3</depth>
	</size>
	<segmented>0</segmented>
	<object>
		<name>helicopter</name>
		<pose>Unspecified</pose>
		<truncated>0</truncated>
		<difficult>0</difficult>
		<occluded>0</occluded>
		<bndbox>
			<xmin>1</xmin>
			<xmax>641</xmax>
			<ymin>19</ymin>
			<ymax>639</ymax>
		</bndbox>
	</object>
</annotation>
