<annotation>
	<folder></folder>
	<filename>img_02_0103_jpg.rf.14b7fd63e0f665c33d2242051b60db5d.jpg</filename>
	<path>img_02_0103_jpg.rf.14b7fd63e0f665c33d2242051b60db5d.jpg</path>
	<source>
		<database>roboflow.ai</database>
	</source>
	<size>
		<width>640</width>
		<height>640</height>
		<depth>3</depth>
	</size>
	<segmented>0</segmented>
	<object>
		<name>Fragata</name>
		<pose>Unspecified</pose>
		<truncated>0</truncated>
		<difficult>0</difficult>
		<occluded>0</occluded>
		<bndbox>
			<xmin>1</xmin>
			<xmax>522</xmax>
			<ymin>1</ymin>
			<ymax>641</ymax>
		</bndbox>
	</object>
</annotation>
