<annotation>
	<folder></folder>
	<filename>img_01_1206_jpg.rf.20f133e385ec1936fe0912ea36ddbc43.jpg</filename>
	<path>img_01_1206_jpg.rf.20f133e385ec1936fe0912ea36ddbc43.jpg</path>
	<source>
		<database>roboflow.ai</database>
	</source>
	<size>
		<width>640</width>
		<height>640</height>
		<depth>3</depth>
	</size>
	<segmented>0</segmented>
	<object>
		<name>Portanaves</name>
		<pose>Unspecified</pose>
		<truncated>0</truncated>
		<difficult>0</difficult>
		<occluded>0</occluded>
		<bndbox>
			<xmin>61</xmin>
			<xmax>636</xmax>
			<ymin>87</ymin>
			<ymax>313</ymax>
		</bndbox>
	</object>
</annotation>
