<annotation>
	<folder></folder>
	<filename>img_02_1088_jpg.rf.da4bf6f0423fc2b6674c23f817f6517f.jpg</filename>
	<path>img_02_1088_jpg.rf.da4bf6f0423fc2b6674c23f817f6517f.jpg</path>
	<source>
		<database>roboflow.ai</database>
	</source>
	<size>
		<width>640</width>
		<height>640</height>
		<depth>3</depth>
	</size>
	<segmented>0</segmented>
	<object>
		<name>Fragata</name>
		<pose>Unspecified</pose>
		<truncated>0</truncated>
		<difficult>0</difficult>
		<occluded>0</occluded>
		<bndbox>
			<xmin>113</xmin>
			<xmax>638</xmax>
			<ymin>203</ymin>
			<ymax>570</ymax>
		</bndbox>
	</object>
</annotation>
