<annotation>
	<folder></folder>
	<filename>img_04_1410_jpg.rf.2a32f1f0921f67be82f306a1737c82b5.jpg</filename>
	<path>img_04_1410_jpg.rf.2a32f1f0921f67be82f306a1737c82b5.jpg</path>
	<source>
		<database>roboflow.ai</database>
	</source>
	<size>
		<width>640</width>
		<height>640</height>
		<depth>3</depth>
	</size>
	<segmented>0</segmented>
	<object>
		<name>tugboat</name>
		<pose>Unspecified</pose>
		<truncated>0</truncated>
		<difficult>0</difficult>
		<occluded>0</occluded>
		<bndbox>
			<xmin>46</xmin>
			<xmax>571</xmax>
			<ymin>315</ymin>
			<ymax>595</ymax>
		</bndbox>
	</object>
</annotation>
