<annotation>
	<folder></folder>
	<filename>00001435_jpg.rf.797a6833e0f73e176dc0d9fa49a78883.jpg</filename>
	<path>00001435_jpg.rf.797a6833e0f73e176dc0d9fa49a78883.jpg</path>
	<source>
		<database>roboflow.ai</database>
	</source>
	<size>
		<width>128</width>
		<height>128</height>
		<depth>3</depth>
	</size>
	<segmented>0</segmented>
	<object>
		<name>helicopter</name>
		<pose>Unspecified</pose>
		<truncated>0</truncated>
		<difficult>0</difficult>
		<occluded>0</occluded>
		<bndbox>
			<xmin>29</xmin>
			<xmax>115</xmax>
			<ymin>51</ymin>
			<ymax>84</ymax>
		</bndbox>
	</object>
	<object>
		<name>helicopter</name>
		<pose>Unspecified</pose>
		<truncated>0</truncated>
		<difficult>0</difficult>
		<occluded>0</occluded>
		<bndbox>
			<xmin>96</xmin>
			<xmax>125</xmax>
			<ymin>41</ymin>
			<ymax>58</ymax>
		</bndbox>
	</object>
</annotation>
