<annotation>
	<folder></folder>
	<filename>img_00_0897_jpg.rf.4c395a107299a6b145a48ef64d0814af.jpg</filename>
	<path>img_00_0897_jpg.rf.4c395a107299a6b145a48ef64d0814af.jpg</path>
	<source>
		<database>roboflow.ai</database>
	</source>
	<size>
		<width>128</width>
		<height>128</height>
		<depth>3</depth>
	</size>
	<segmented>0</segmented>
	<object>
		<name>submarine</name>
		<pose>Unspecified</pose>
		<truncated>0</truncated>
		<difficult>0</difficult>
		<occluded>0</occluded>
		<bndbox>
			<xmin>3</xmin>
			<xmax>125</xmax>
			<ymin>57</ymin>
			<ymax>87</ymax>
		</bndbox>
	</object>
</annotation>
