<annotation>
	<folder></folder>
	<filename>img_02_0239_jpg.rf.86993993b9a25dee77553b7c4e2b8c63.jpg</filename>
	<path>img_02_0239_jpg.rf.86993993b9a25dee77553b7c4e2b8c63.jpg</path>
	<source>
		<database>roboflow.ai</database>
	</source>
	<size>
		<width>128</width>
		<height>128</height>
		<depth>3</depth>
	</size>
	<segmented>0</segmented>
	<object>
		<name>Fragata</name>
		<pose>Unspecified</pose>
		<truncated>0</truncated>
		<difficult>0</difficult>
		<occluded>0</occluded>
		<bndbox>
			<xmin>4</xmin>
			<xmax>125</xmax>
			<ymin>35</ymin>
			<ymax>87</ymax>
		</bndbox>
	</object>
</annotation>
