<annotation>
	<folder></folder>
	<filename>img_01_0669_jpg.rf.3aca5178f11ac2465e7adeb877001e13.jpg</filename>
	<path>img_01_0669_jpg.rf.3aca5178f11ac2465e7adeb877001e13.jpg</path>
	<source>
		<database>roboflow.ai</database>
	</source>
	<size>
		<width>128</width>
		<height>128</height>
		<depth>3</depth>
	</size>
	<segmented>0</segmented>
	<object>
		<name>Portanaves</name>
		<pose>Unspecified</pose>
		<truncated>0</truncated>
		<difficult>0</difficult>
		<occluded>0</occluded>
		<bndbox>
			<xmin>12</xmin>
			<xmax>128</xmax>
			<ymin>6</ymin>
			<ymax>113</ymax>
		</bndbox>
	</object>
</annotation>
