<annotation>
	<folder></folder>
	<filename>img_00_0399_jpg.rf.73c89c35725e82c703d7cf370aaa6175.jpg</filename>
	<path>img_00_0399_jpg.rf.73c89c35725e82c703d7cf370aaa6175.jpg</path>
	<source>
		<database>roboflow.ai</database>
	</source>
	<size>
		<width>128</width>
		<height>128</height>
		<depth>3</depth>
	</size>
	<segmented>0</segmented>
	<object>
		<name>submarine</name>
		<pose>Unspecified</pose>
		<truncated>0</truncated>
		<difficult>0</difficult>
		<occluded>0</occluded>
		<bndbox>
			<xmin>58</xmin>
			<xmax>91</xmax>
			<ymin>40</ymin>
			<ymax>103</ymax>
		</bndbox>
	</object>
	<object>
		<name>submarine</name>
		<pose>Unspecified</pose>
		<truncated>0</truncated>
		<difficult>0</difficult>
		<occluded>0</occluded>
		<bndbox>
			<xmin>39</xmin>
			<xmax>79</xmax>
			<ymin>34</ymin>
			<ymax>106</ymax>
		</bndbox>
	</object>
</annotation>
