<annotation>
	<folder></folder>
	<filename>img_01_0112_jpg.rf.f86fd932ccaa65c5eefce979499e7afa.jpg</filename>
	<path>img_01_0112_jpg.rf.f86fd932ccaa65c5eefce979499e7afa.jpg</path>
	<source>
		<database>roboflow.ai</database>
	</source>
	<size>
		<width>128</width>
		<height>128</height>
		<depth>3</depth>
	</size>
	<segmented>0</segmented>
	<object>
		<name>Portanaves</name>
		<pose>Unspecified</pose>
		<truncated>0</truncated>
		<difficult>0</difficult>
		<occluded>0</occluded>
		<bndbox>
			<xmin>7</xmin>
			<xmax>117</xmax>
			<ymin>20</ymin>
			<ymax>109</ymax>
		</bndbox>
	</object>
</annotation>
