<annotation>
	<folder></folder>
	<filename>img_02_1231_jpg.rf.b1561a282a570bf87055dd3c76605469.jpg</filename>
	<path>img_02_1231_jpg.rf.b1561a282a570bf87055dd3c76605469.jpg</path>
	<source>
		<database>roboflow.ai</database>
	</source>
	<size>
		<width>128</width>
		<height>128</height>
		<depth>3</depth>
	</size>
	<segmented>0</segmented>
	<object>
		<name>Fragata</name>
		<pose>Unspecified</pose>
		<truncated>0</truncated>
		<difficult>0</difficult>
		<occluded>0</occluded>
		<bndbox>
			<xmin>9</xmin>
			<xmax>123</xmax>
			<ymin>37</ymin>
			<ymax>91</ymax>
		</bndbox>
	</object>
</annotation>
