<annotation>
	<folder></folder>
	<filename>img_02_0131_jpg.rf.5dc70ca0d36ee4e0e401059a99bdba6f.jpg</filename>
	<path>img_02_0131_jpg.rf.5dc70ca0d36ee4e0e401059a99bdba6f.jpg</path>
	<source>
		<database>roboflow.ai</database>
	</source>
	<size>
		<width>128</width>
		<height>128</height>
		<depth>3</depth>
	</size>
	<segmented>0</segmented>
	<object>
		<name>Fragata</name>
		<pose>Unspecified</pose>
		<truncated>0</truncated>
		<difficult>0</difficult>
		<occluded>0</occluded>
		<bndbox>
			<xmin>10</xmin>
			<xmax>124</xmax>
			<ymin>11</ymin>
			<ymax>78</ymax>
		</bndbox>
	</object>
</annotation>
