<annotation>
	<folder></folder>
	<filename>img_00_1225_jpg.rf.44ec6bef877f71257090cd69d27eeb5d.jpg</filename>
	<path>img_00_1225_jpg.rf.44ec6bef877f71257090cd69d27eeb5d.jpg</path>
	<source>
		<database>roboflow.ai</database>
	</source>
	<size>
		<width>128</width>
		<height>128</height>
		<depth>3</depth>
	</size>
	<segmented>0</segmented>
	<object>
		<name>submarine</name>
		<pose>Unspecified</pose>
		<truncated>0</truncated>
		<difficult>0</difficult>
		<occluded>0</occluded>
		<bndbox>
			<xmin>7</xmin>
			<xmax>123</xmax>
			<ymin>75</ymin>
			<ymax>92</ymax>
		</bndbox>
	</object>
</annotation>
