<annotation>
	<folder></folder>
	<filename>img_04_0184_jpg.rf.68c0a66e213f1843f6f7025c4f743101.jpg</filename>
	<path>img_04_0184_jpg.rf.68c0a66e213f1843f6f7025c4f743101.jpg</path>
	<source>
		<database>roboflow.ai</database>
	</source>
	<size>
		<width>256</width>
		<height>256</height>
		<depth>3</depth>
	</size>
	<segmented>0</segmented>
	<object>
		<name>tugboat</name>
		<pose>Unspecified</pose>
		<truncated>0</truncated>
		<difficult>0</difficult>
		<occluded>0</occluded>
		<bndbox>
			<xmin>26</xmin>
			<xmax>234</xmax>
			<ymin>5</ymin>
			<ymax>229</ymax>
		</bndbox>
	</object>
</annotation>
