<annotation>
	<folder></folder>
	<filename>img_01_0841_jpg.rf.b104839c57fe8661dccb2425adae9a52.jpg</filename>
	<path>img_01_0841_jpg.rf.b104839c57fe8661dccb2425adae9a52.jpg</path>
	<source>
		<database>roboflow.ai</database>
	</source>
	<size>
		<width>256</width>
		<height>256</height>
		<depth>3</depth>
	</size>
	<segmented>0</segmented>
	<object>
		<name>Portanaves</name>
		<pose>Unspecified</pose>
		<truncated>0</truncated>
		<difficult>0</difficult>
		<occluded>0</occluded>
		<bndbox>
			<xmin>21</xmin>
			<xmax>249</xmax>
			<ymin>14</ymin>
			<ymax>229</ymax>
		</bndbox>
	</object>
</annotation>
