<annotation>
	<folder></folder>
	<filename>img_01_0911_jpg.rf.a596bfeab4fe2c70b0eec8dac9bdd127.jpg</filename>
	<path>img_01_0911_jpg.rf.a596bfeab4fe2c70b0eec8dac9bdd127.jpg</path>
	<source>
		<database>roboflow.ai</database>
	</source>
	<size>
		<width>256</width>
		<height>256</height>
		<depth>3</depth>
	</size>
	<segmented>0</segmented>
	<object>
		<name>Portanaves</name>
		<pose>Unspecified</pose>
		<truncated>0</truncated>
		<difficult>0</difficult>
		<occluded>0</occluded>
		<bndbox>
			<xmin>5</xmin>
			<xmax>253</xmax>
			<ymin>72</ymin>
			<ymax>169</ymax>
		</bndbox>
	</object>
</annotation>
