<annotation>
	<folder></folder>
	<filename>img_02_0251_jpg.rf.aac2ba41fe1913dff37976aacddeac6c.jpg</filename>
	<path>img_02_0251_jpg.rf.aac2ba41fe1913dff37976aacddeac6c.jpg</path>
	<source>
		<database>roboflow.ai</database>
	</source>
	<size>
		<width>256</width>
		<height>256</height>
		<depth>3</depth>
	</size>
	<segmented>0</segmented>
	<object>
		<name>Fragata</name>
		<pose>Unspecified</pose>
		<truncated>0</truncated>
		<difficult>0</difficult>
		<occluded>0</occluded>
		<bndbox>
			<xmin>4</xmin>
			<xmax>247</xmax>
			<ymin>52</ymin>
			<ymax>192</ymax>
		</bndbox>
	</object>
</annotation>
