<annotation>
	<folder></folder>
	<filename>img_03_0678_jpg.rf.f99408f67605aef5048c111abd949f3e.jpg</filename>
	<path>img_03_0678_jpg.rf.f99408f67605aef5048c111abd949f3e.jpg</path>
	<source>
		<database>roboflow.ai</database>
	</source>
	<size>
		<width>256</width>
		<height>256</height>
		<depth>3</depth>
	</size>
	<segmented>0</segmented>
	<object>
		<name>cruises</name>
		<pose>Unspecified</pose>
		<truncated>0</truncated>
		<difficult>0</difficult>
		<occluded>0</occluded>
		<bndbox>
			<xmin>20</xmin>
			<xmax>219</xmax>
			<ymin>74</ymin>
			<ymax>228</ymax>
		</bndbox>
	</object>
</annotation>
