<annotation>
	<folder></folder>
	<filename>img_02_0338_jpg.rf.46e885a059ccae570322f46d78e0eb03.jpg</filename>
	<path>img_02_0338_jpg.rf.46e885a059ccae570322f46d78e0eb03.jpg</path>
	<source>
		<database>roboflow.ai</database>
	</source>
	<size>
		<width>256</width>
		<height>256</height>
		<depth>3</depth>
	</size>
	<segmented>0</segmented>
	<object>
		<name>Fragata</name>
		<pose>Unspecified</pose>
		<truncated>0</truncated>
		<difficult>0</difficult>
		<occluded>0</occluded>
		<bndbox>
			<xmin>20</xmin>
			<xmax>232</xmax>
			<ymin>79</ymin>
			<ymax>177</ymax>
		</bndbox>
	</object>
</annotation>
