<annotation>
	<folder></folder>
	<filename>img_02_0731_jpg.rf.3f95c295dc27b2e523a9a87f4f50d90e.jpg</filename>
	<path>img_02_0731_jpg.rf.3f95c295dc27b2e523a9a87f4f50d90e.jpg</path>
	<source>
		<database>roboflow.ai</database>
	</source>
	<size>
		<width>256</width>
		<height>256</height>
		<depth>3</depth>
	</size>
	<segmented>0</segmented>
	<object>
		<name>Fragata</name>
		<pose>Unspecified</pose>
		<truncated>0</truncated>
		<difficult>0</difficult>
		<occluded>0</occluded>
		<bndbox>
			<xmin>44</xmin>
			<xmax>203</xmax>
			<ymin>25</ymin>
			<ymax>235</ymax>
		</bndbox>
	</object>
</annotation>
