<annotation>
	<folder></folder>
	<filename>img_01_0452_jpg.rf.9e6c86411ca47416dcc0e826b27d830c.jpg</filename>
	<path>img_01_0452_jpg.rf.9e6c86411ca47416dcc0e826b27d830c.jpg</path>
	<source>
		<database>roboflow.ai</database>
	</source>
	<size>
		<width>256</width>
		<height>256</height>
		<depth>3</depth>
	</size>
	<segmented>0</segmented>
	<object>
		<name>Portanaves</name>
		<pose>Unspecified</pose>
		<truncated>0</truncated>
		<difficult>0</difficult>
		<occluded>0</occluded>
		<bndbox>
			<xmin>28</xmin>
			<xmax>219</xmax>
			<ymin>18</ymin>
			<ymax>213</ymax>
		</bndbox>
	</object>
</annotation>
