<annotation>
	<folder></folder>
	<filename>img_01_0882_jpg.rf.ff3a95b0c5ba76e13bf0db61fb0f90ea.jpg</filename>
	<path>img_01_0882_jpg.rf.ff3a95b0c5ba76e13bf0db61fb0f90ea.jpg</path>
	<source>
		<database>roboflow.ai</database>
	</source>
	<size>
		<width>256</width>
		<height>256</height>
		<depth>3</depth>
	</size>
	<segmented>0</segmented>
	<object>
		<name>Portanaves</name>
		<pose>Unspecified</pose>
		<truncated>0</truncated>
		<difficult>0</difficult>
		<occluded>0</occluded>
		<bndbox>
			<xmin>9</xmin>
			<xmax>247</xmax>
			<ymin>24</ymin>
			<ymax>182</ymax>
		</bndbox>
	</object>
</annotation>
