<annotation>
	<folder></folder>
	<filename>00001436_jpg.rf.556fa7c129d35e60da1af1156ad51c60.jpg</filename>
	<path>00001436_jpg.rf.556fa7c129d35e60da1af1156ad51c60.jpg</path>
	<source>
		<database>roboflow.ai</database>
	</source>
	<size>
		<width>640</width>
		<height>640</height>
		<depth>3</depth>
	</size>
	<segmented>0</segmented>
	<object>
		<name>helicopter</name>
		<pose>Unspecified</pose>
		<truncated>0</truncated>
		<difficult>0</difficult>
		<occluded>0</occluded>
		<bndbox>
			<xmin>49</xmin>
			<xmax>584</xmax>
			<ymin>23</ymin>
			<ymax>591</ymax>
		</bndbox>
	</object>
</annotation>
