<annotation>
	<folder></folder>
	<filename>img_02_0469_jpg.rf.d8bf9955f0c0eb36d0f801fd1d2209dd.jpg</filename>
	<path>img_02_0469_jpg.rf.d8bf9955f0c0eb36d0f801fd1d2209dd.jpg</path>
	<source>
		<database>roboflow.ai</database>
	</source>
	<size>
		<width>640</width>
		<height>640</height>
		<depth>3</depth>
	</size>
	<segmented>0</segmented>
	<object>
		<name>Fragata</name>
		<pose>Unspecified</pose>
		<truncated>0</truncated>
		<difficult>0</difficult>
		<occluded>0</occluded>
		<bndbox>
			<xmin>110</xmin>
			<xmax>542</xmax>
			<ymin>100</ymin>
			<ymax>461</ymax>
		</bndbox>
	</object>
</annotation>
