<annotation>
	<folder></folder>
	<filename>img_01_1208_jpg.rf.00c1032d0a4f060d55a2b49736cbdd56.jpg</filename>
	<path>img_01_1208_jpg.rf.00c1032d0a4f060d55a2b49736cbdd56.jpg</path>
	<source>
		<database>roboflow.ai</database>
	</source>
	<size>
		<width>512</width>
		<height>512</height>
		<depth>3</depth>
	</size>
	<segmented>0</segmented>
	<object>
		<name>Portanaves</name>
		<pose>Unspecified</pose>
		<truncated>0</truncated>
		<difficult>0</difficult>
		<occluded>0</occluded>
		<bndbox>
			<xmin>15</xmin>
			<xmax>513</xmax>
			<ymin>3</ymin>
			<ymax>413</ymax>
		</bndbox>
	</object>
</annotation>
