<annotation>
	<folder></folder>
	<filename>img_02_0217_jpg.rf.de31dd3682b0b17d461fe6d08c5fe6c0.jpg</filename>
	<path>img_02_0217_jpg.rf.de31dd3682b0b17d461fe6d08c5fe6c0.jpg</path>
	<source>
		<database>roboflow.ai</database>
	</source>
	<size>
		<width>512</width>
		<height>512</height>
		<depth>3</depth>
	</size>
	<segmented>0</segmented>
	<object>
		<name>Fragata</name>
		<pose>Unspecified</pose>
		<truncated>0</truncated>
		<difficult>0</difficult>
		<occluded>0</occluded>
		<bndbox>
			<xmin>305</xmin>
			<xmax>513</xmax>
			<ymin>130</ymin>
			<ymax>343</ymax>
		</bndbox>
	</object>
</annotation>
