<annotation>
	<folder></folder>
	<filename>img_00_1135_jpg.rf.5f840bb2e58fa3500d413fa3a11dbfad.jpg</filename>
	<path>img_00_1135_jpg.rf.5f840bb2e58fa3500d413fa3a11dbfad.jpg</path>
	<source>
		<database>roboflow.ai</database>
	</source>
	<size>
		<width>512</width>
		<height>512</height>
		<depth>3</depth>
	</size>
	<segmented>0</segmented>
	<object>
		<name>submarine</name>
		<pose>Unspecified</pose>
		<truncated>0</truncated>
		<difficult>0</difficult>
		<occluded>0</occluded>
		<bndbox>
			<xmin>1</xmin>
			<xmax>513</xmax>
			<ymin>219</ymin>
			<ymax>495</ymax>
		</bndbox>
	</object>
</annotation>
