<annotation>
	<folder></folder>
	<filename>img_02_0235_jpg.rf.402d9875b6402981b43ab8c639a8fe80.jpg</filename>
	<path>img_02_0235_jpg.rf.402d9875b6402981b43ab8c639a8fe80.jpg</path>
	<source>
		<database>roboflow.ai</database>
	</source>
	<size>
		<width>512</width>
		<height>512</height>
		<depth>3</depth>
	</size>
	<segmented>0</segmented>
	<object>
		<name>Fragata</name>
		<pose>Unspecified</pose>
		<truncated>0</truncated>
		<difficult>0</difficult>
		<occluded>0</occluded>
		<bndbox>
			<xmin>67</xmin>
			<xmax>409</xmax>
			<ymin>1</ymin>
			<ymax>513</ymax>
		</bndbox>
	</object>
</annotation>
