<annotation>
	<folder></folder>
	<filename>img_04_0198_jpg.rf.85b0df5105b1f0fd40c45a61a9f38178.jpg</filename>
	<path>img_04_0198_jpg.rf.85b0df5105b1f0fd40c45a61a9f38178.jpg</path>
	<source>
		<database>roboflow.ai</database>
	</source>
	<size>
		<width>512</width>
		<height>512</height>
		<depth>3</depth>
	</size>
	<segmented>0</segmented>
	<object>
		<name>tugboat</name>
		<pose>Unspecified</pose>
		<truncated>0</truncated>
		<difficult>0</difficult>
		<occluded>0</occluded>
		<bndbox>
			<xmin>1</xmin>
			<xmax>473</xmax>
			<ymin>1</ymin>
			<ymax>513</ymax>
		</bndbox>
	</object>
</annotation>
