<annotation>
	<folder></folder>
	<filename>img_04_1467_jpg.rf.74333d30ce130cb089b28d2a8f7cbb9c.jpg</filename>
	<path>img_04_1467_jpg.rf.74333d30ce130cb089b28d2a8f7cbb9c.jpg</path>
	<source>
		<database>roboflow.ai</database>
	</source>
	<size>
		<width>512</width>
		<height>512</height>
		<depth>3</depth>
	</size>
	<segmented>0</segmented>
	<object>
		<name>tugboat</name>
		<pose>Unspecified</pose>
		<truncated>0</truncated>
		<difficult>0</difficult>
		<occluded>0</occluded>
		<bndbox>
			<xmin>1</xmin>
			<xmax>436</xmax>
			<ymin>165</ymin>
			<ymax>513</ymax>
		</bndbox>
	</object>
</annotation>
