<annotation>
	<folder></folder>
	<filename>img_03_0860_jpg.rf.7810a3280ce3034737c06ab167bb0de9.jpg</filename>
	<path>img_03_0860_jpg.rf.7810a3280ce3034737c06ab167bb0de9.jpg</path>
	<source>
		<database>roboflow.ai</database>
	</source>
	<size>
		<width>512</width>
		<height>512</height>
		<depth>3</depth>
	</size>
	<segmented>0</segmented>
	<object>
		<name>cruises</name>
		<pose>Unspecified</pose>
		<truncated>0</truncated>
		<difficult>0</difficult>
		<occluded>0</occluded>
		<bndbox>
			<xmin>12</xmin>
			<xmax>513</xmax>
			<ymin>22</ymin>
			<ymax>513</ymax>
		</bndbox>
	</object>
</annotation>
