<annotation>
	<folder></folder>
	<filename>img_00_0921_jpg.rf.ef5095186a9109cbfa675f7331264ad6.jpg</filename>
	<path>img_00_0921_jpg.rf.ef5095186a9109cbfa675f7331264ad6.jpg</path>
	<source>
		<database>roboflow.ai</database>
	</source>
	<size>
		<width>512</width>
		<height>512</height>
		<depth>3</depth>
	</size>
	<segmented>0</segmented>
	<object>
		<name>submarine</name>
		<pose>Unspecified</pose>
		<truncated>0</truncated>
		<difficult>0</difficult>
		<occluded>0</occluded>
		<bndbox>
			<xmin>135</xmin>
			<xmax>471</xmax>
			<ymin>53</ymin>
			<ymax>448</ymax>
		</bndbox>
	</object>
</annotation>
