<annotation>
	<folder></folder>
	<filename>img_02_0227_jpg.rf.ac9c5f46d3b9c7444422dc73d5c23531.jpg</filename>
	<path>img_02_0227_jpg.rf.ac9c5f46d3b9c7444422dc73d5c23531.jpg</path>
	<source>
		<database>roboflow.ai</database>
	</source>
	<size>
		<width>512</width>
		<height>512</height>
		<depth>3</depth>
	</size>
	<segmented>0</segmented>
	<object>
		<name>Fragata</name>
		<pose>Unspecified</pose>
		<truncated>0</truncated>
		<difficult>0</difficult>
		<occluded>0</occluded>
		<bndbox>
			<xmin>1</xmin>
			<xmax>513</xmax>
			<ymin>1</ymin>
			<ymax>386</ymax>
		</bndbox>
	</object>
</annotation>
