<annotation>
	<folder></folder>
	<filename>img_03_1401_jpg.rf.d29af0162ef104dcad879412fa447842.jpg</filename>
	<path>img_03_1401_jpg.rf.d29af0162ef104dcad879412fa447842.jpg</path>
	<source>
		<database>roboflow.ai</database>
	</source>
	<size>
		<width>128</width>
		<height>128</height>
		<depth>3</depth>
	</size>
	<segmented>0</segmented>
	<object>
		<name>cruises</name>
		<pose>Unspecified</pose>
		<truncated>0</truncated>
		<difficult>0</difficult>
		<occluded>0</occluded>
		<bndbox>
			<xmin>9</xmin>
			<xmax>120</xmax>
			<ymin>28</ymin>
			<ymax>115</ymax>
		</bndbox>
	</object>
</annotation>
