<annotation>
	<folder></folder>
	<filename>img_03_0704_jpg.rf.8145be380633ba644f5ab405cdb53bba.jpg</filename>
	<path>img_03_0704_jpg.rf.8145be380633ba644f5ab405cdb53bba.jpg</path>
	<source>
		<database>roboflow.ai</database>
	</source>
	<size>
		<width>128</width>
		<height>128</height>
		<depth>3</depth>
	</size>
	<segmented>0</segmented>
	<object>
		<name>cruises</name>
		<pose>Unspecified</pose>
		<truncated>0</truncated>
		<difficult>0</difficult>
		<occluded>0</occluded>
		<bndbox>
			<xmin>3</xmin>
			<xmax>126</xmax>
			<ymin>31</ymin>
			<ymax>125</ymax>
		</bndbox>
	</object>
</annotation>
